nl2sparql/__init__.py
nl2sparql/__main__.py
nl2sparql/cli.py
nl2sparql/config.py
nl2sparql/agent/__init__.py
nl2sparql/agent/graph.py
nl2sparql/agent/nodes.py
nl2sparql/agent/state.py
nl2sparql/constraints/__init__.py
nl2sparql/constraints/base.py
nl2sparql/constraints/compositional.py
nl2sparql/constraints/emotion.py
nl2sparql/constraints/lexical_relation.py
nl2sparql/constraints/multi_entry.py
nl2sparql/constraints/prompt_builder.py
nl2sparql/constraints/semantic.py
nl2sparql/constraints/translation.py
nl2sparql/data/ontology.json
nl2sparql/data/sparql_queries_examples.json
nl2sparql/data/test_dataset.json
nl2sparql/evaluation/__init__.py
nl2sparql/evaluation/batch_evaluate.py
nl2sparql/evaluation/evaluate.py
nl2sparql/generation/__init__.py
nl2sparql/generation/adapters.py
nl2sparql/generation/synthesizer.py
nl2sparql/llm/__init__.py
nl2sparql/llm/anthropic_client.py
nl2sparql/llm/base.py
nl2sparql/llm/gemini_client.py
nl2sparql/llm/mistral_client.py
nl2sparql/llm/ollama_client.py
nl2sparql/llm/openai_client.py
nl2sparql/mcp/__init__.py
nl2sparql/mcp/__main__.py
nl2sparql/mcp/resources.py
nl2sparql/mcp/server.py
nl2sparql/mcp/tools.py
nl2sparql/retrieval/__init__.py
nl2sparql/retrieval/bm25.py
nl2sparql/retrieval/embeddings.py
nl2sparql/retrieval/hybrid_retriever.py
nl2sparql/retrieval/ontology_retriever.py
nl2sparql/retrieval/patterns.py
nl2sparql/synthetic/__init__.py
nl2sparql/synthetic/generator.py
nl2sparql/validation/__init__.py
nl2sparql/validation/endpoint.py
nl2sparql/validation/semantic.py
nl2sparql/validation/syntax.py
liita_nl2sparql-0.7.1.dist-info/METADATA
liita_nl2sparql-0.7.1.dist-info/WHEEL
liita_nl2sparql-0.7.1.dist-info/entry_points.txt
liita_nl2sparql-0.7.1.dist-info/licenses/LICENSE
liita_nl2sparql-0.7.1.dist-info/RECORD
