Metadata-Version: 2.4
Name: liita-nl2sparql
Version: 0.7.1
Summary: Natural Language to SPARQL translation for the LiITA knowledge base
Project-URL: Homepage, https://github.com/tonazzog/nl2sparql
Project-URL: Documentation, https://github.com/tonazzog/nl2sparql#readme
Project-URL: Repository, https://github.com/tonazzog/nl2sparql
Author: Giovanna Tonazzo
License-Expression: MIT
License-File: LICENSE
Keywords: italian,knowledge-base,linguistics,nlp,sparql
Classifier: Development Status :: 3 - Alpha
Classifier: Intended Audience :: Science/Research
Classifier: License :: OSI Approved :: MIT License
Classifier: Programming Language :: Python :: 3
Classifier: Programming Language :: Python :: 3.10
Classifier: Programming Language :: Python :: 3.11
Classifier: Programming Language :: Python :: 3.12
Classifier: Topic :: Scientific/Engineering :: Artificial Intelligence
Requires-Python: >=3.10
Requires-Dist: click>=8.0.0
Requires-Dist: faiss-cpu>=1.7.0
Requires-Dist: numpy>=1.21.0
Requires-Dist: rank-bm25>=0.2.0
Requires-Dist: rdflib>=6.0.0
Requires-Dist: sentence-transformers>=2.2.0
Requires-Dist: sparqlwrapper>=2.0.0
Provides-Extra: agent
Requires-Dist: langchain-core>=0.3.0; extra == 'agent'
Requires-Dist: langgraph>=0.2.0; extra == 'agent'
Provides-Extra: agent-all
Requires-Dist: langchain-anthropic>=0.2.0; extra == 'agent-all'
Requires-Dist: langchain-core>=0.3.0; extra == 'agent-all'
Requires-Dist: langchain-google-genai>=2.0.0; extra == 'agent-all'
Requires-Dist: langchain-mistralai>=0.1.0; extra == 'agent-all'
Requires-Dist: langchain-ollama>=0.2.0; extra == 'agent-all'
Requires-Dist: langchain-openai>=0.2.0; extra == 'agent-all'
Requires-Dist: langgraph>=0.2.0; extra == 'agent-all'
Provides-Extra: agent-anthropic
Requires-Dist: langchain-anthropic>=0.2.0; extra == 'agent-anthropic'
Requires-Dist: langchain-core>=0.3.0; extra == 'agent-anthropic'
Requires-Dist: langgraph>=0.2.0; extra == 'agent-anthropic'
Provides-Extra: agent-gemini
Requires-Dist: langchain-core>=0.3.0; extra == 'agent-gemini'
Requires-Dist: langchain-google-genai>=2.0.0; extra == 'agent-gemini'
Requires-Dist: langgraph>=0.2.0; extra == 'agent-gemini'
Provides-Extra: agent-mistral
Requires-Dist: langchain-core>=0.3.0; extra == 'agent-mistral'
Requires-Dist: langchain-mistralai>=0.1.0; extra == 'agent-mistral'
Requires-Dist: langgraph>=0.2.0; extra == 'agent-mistral'
Provides-Extra: agent-ollama
Requires-Dist: langchain-core>=0.3.0; extra == 'agent-ollama'
Requires-Dist: langchain-ollama>=0.2.0; extra == 'agent-ollama'
Requires-Dist: langgraph>=0.2.0; extra == 'agent-ollama'
Provides-Extra: agent-openai
Requires-Dist: langchain-core>=0.3.0; extra == 'agent-openai'
Requires-Dist: langchain-openai>=0.2.0; extra == 'agent-openai'
Requires-Dist: langgraph>=0.2.0; extra == 'agent-openai'
Provides-Extra: all
Requires-Dist: anthropic>=0.18.0; extra == 'all'
Requires-Dist: datasets>=2.14.0; extra == 'all'
Requires-Dist: google-generativeai>=0.3.0; extra == 'all'
Requires-Dist: gradio>=4.0.0; extra == 'all'
Requires-Dist: langchain-anthropic>=0.2.0; extra == 'all'
Requires-Dist: langchain-core>=0.3.0; extra == 'all'
Requires-Dist: langchain-google-genai>=2.0.0; extra == 'all'
Requires-Dist: langchain-mistralai>=0.1.0; extra == 'all'
Requires-Dist: langchain-ollama>=0.2.0; extra == 'all'
Requires-Dist: langchain-openai>=0.2.0; extra == 'all'
Requires-Dist: langgraph>=0.2.0; extra == 'all'
Requires-Dist: mcp>=1.0.0; extra == 'all'
Requires-Dist: mistralai>=0.0.7; extra == 'all'
Requires-Dist: ollama>=0.1.0; extra == 'all'
Requires-Dist: openai>=1.0.0; extra == 'all'
Provides-Extra: anthropic
Requires-Dist: anthropic>=0.18.0; extra == 'anthropic'
Provides-Extra: dev
Requires-Dist: black>=23.0.0; extra == 'dev'
Requires-Dist: pytest-cov>=4.0.0; extra == 'dev'
Requires-Dist: pytest>=7.0.0; extra == 'dev'
Requires-Dist: ruff>=0.1.0; extra == 'dev'
Provides-Extra: gemini
Requires-Dist: google-generativeai>=0.3.0; extra == 'gemini'
Provides-Extra: mcp
Requires-Dist: mcp>=1.0.0; extra == 'mcp'
Provides-Extra: mcp-all
Requires-Dist: anthropic>=0.18.0; extra == 'mcp-all'
Requires-Dist: google-generativeai>=0.3.0; extra == 'mcp-all'
Requires-Dist: mcp>=1.0.0; extra == 'mcp-all'
Requires-Dist: mistralai>=0.0.7; extra == 'mcp-all'
Requires-Dist: ollama>=0.1.0; extra == 'mcp-all'
Requires-Dist: openai>=1.0.0; extra == 'mcp-all'
Provides-Extra: mcp-anthropic
Requires-Dist: anthropic>=0.18.0; extra == 'mcp-anthropic'
Requires-Dist: mcp>=1.0.0; extra == 'mcp-anthropic'
Provides-Extra: mcp-gemini
Requires-Dist: google-generativeai>=0.3.0; extra == 'mcp-gemini'
Requires-Dist: mcp>=1.0.0; extra == 'mcp-gemini'
Provides-Extra: mcp-mistral
Requires-Dist: mcp>=1.0.0; extra == 'mcp-mistral'
Requires-Dist: mistralai>=0.0.7; extra == 'mcp-mistral'
Provides-Extra: mcp-ollama
Requires-Dist: mcp>=1.0.0; extra == 'mcp-ollama'
Requires-Dist: ollama>=0.1.0; extra == 'mcp-ollama'
Provides-Extra: mcp-openai
Requires-Dist: mcp>=1.0.0; extra == 'mcp-openai'
Requires-Dist: openai>=1.0.0; extra == 'mcp-openai'
Provides-Extra: mistral
Requires-Dist: mistralai>=0.0.7; extra == 'mistral'
Provides-Extra: ollama
Requires-Dist: ollama>=0.1.0; extra == 'ollama'
Provides-Extra: openai
Requires-Dist: openai>=1.0.0; extra == 'openai'
Provides-Extra: synthetic
Requires-Dist: datasets>=2.14.0; extra == 'synthetic'
Requires-Dist: langchain-core>=0.3.0; extra == 'synthetic'
Requires-Dist: langgraph>=0.2.0; extra == 'synthetic'
Provides-Extra: ui
Requires-Dist: gradio>=4.0.0; extra == 'ui'
